{
  "type": "farmersdelight:cooking",
  "cookingtime": 200,
  "experience": 0.35,
  "ingredients": [
    {
      "item": "minecraft:brown_mushroom"
    },
    {
      "item": "minecraft:brown_mushroom"
    },
    {
      "item": "minecraft:torchflower"
    },
    {
      "item": "immortalers_delight:pitcher_pod_petal"
    },
    {
      "item": "immortalers_delight:pitcher_pod_petal"
    },
    {
      "tag": "forge:dough"
    }
  ],
  "result": {
    "item": "immortalers_delight:roasted_mushroom_pizza"
  }
}